open_quant_app/__init__.py
open_quant_app/main.py
open_quant_app/backtest/BackTester.py
open_quant_app/backtest/__init__.py
open_quant_app/core/QuantApp.py
open_quant_app/core/__init__.py
open_quant_app/data/__init__.py
open_quant_app/manager/OrderManager.py
open_quant_app/manager/OrderManagerV2.py
open_quant_app/manager/PositionManager.py
open_quant_app/manager/__init__.py
open_quant_app/model/BarData.py
open_quant_app/model/__init__.py
open_quant_app/strategy/Strategy.py
open_quant_app/strategy/__init__.py
open_quant_app/trade/CommonTradeCallback.py
open_quant_app/trade/Trader.py
open_quant_app/trade/__init__.py
open_quant_app/utils/ConfigUtils.py
open_quant_app/utils/DownloadUtils.py
open_quant_app/utils/FixedQueue.py
open_quant_app/utils/LogUtils.py
open_quant_app/utils/OrderFilter.py
open_quant_app/utils/TimeUtils.py
open_quant_app/utils/__init__.py
open_quant_app-0.1.5.5.dist-info/LICENSE
open_quant_app-0.1.5.5.dist-info/METADATA
open_quant_app-0.1.5.5.dist-info/WHEEL
open_quant_app-0.1.5.5.dist-info/top_level.txt
open_quant_app-0.1.5.5.dist-info/RECORD
