Metadata-Version: 2.1
Name: open-quant-app
Version: 0.1.5.5
Summary: A quantitative trading framework.
Home-page: https://github.com/openhe-hub/open-quant-app
Author: openhe
Author-email: 625529334@qq.com
License: MIT
Keywords: quantitative trading finance
License-File: LICENSE
Requires-Dist: numpy
Requires-Dist: pandas
Requires-Dist: matplotlib
Requires-Dist: dash
Requires-Dist: loguru
Requires-Dist: toml
